llm_cmd.py
llm_cmd-0.2a0.dist-info/LICENSE
llm_cmd-0.2a0.dist-info/METADATA
llm_cmd-0.2a0.dist-info/WHEEL
llm_cmd-0.2a0.dist-info/entry_points.txt
llm_cmd-0.2a0.dist-info/top_level.txt
llm_cmd-0.2a0.dist-info/RECORD
