Metadata-Version: 2.1
Name: llm-cmd
Version: 0.2a0
Summary: Use LLM to generate and execute commands in your shell
Author: Simon Willison
License: Apache-2.0
Project-URL: Homepage, https://github.com/simonw/llm-cmd
Project-URL: Changelog, https://github.com/simonw/llm-cmd/releases
Project-URL: Issues, https://github.com/simonw/llm-cmd/issues
Project-URL: CI, https://github.com/simonw/llm-cmd/actions
Classifier: License :: OSI Approved :: Apache Software License
License-File: LICENSE
Requires-Dist: llm
Requires-Dist: prompt-toolkit >=3.0.43
Requires-Dist: pygments >=2.17.2
Provides-Extra: test
Requires-Dist: pytest ; extra == 'test'
